iotedgehubdev/__init__.py
iotedgehubdev/certutils.py
iotedgehubdev/cli.py
iotedgehubdev/compose_parser.py
iotedgehubdev/composeproject.py
iotedgehubdev/configs.py
iotedgehubdev/constants.py
iotedgehubdev/decorators.py
iotedgehubdev/edgecert.py
iotedgehubdev/edgedockerclient.py
iotedgehubdev/edgemanager.py
iotedgehubdev/errors.py
iotedgehubdev/hostplatform.py
iotedgehubdev/output.py
iotedgehubdev/telemetry.py
iotedgehubdev/telemetry_upload.py
iotedgehubdev/utils.py
iotedgehubdev-0.14.18.dist-info/LICENSE
iotedgehubdev-0.14.18.dist-info/METADATA
iotedgehubdev-0.14.18.dist-info/WHEEL
iotedgehubdev-0.14.18.dist-info/entry_points.txt
iotedgehubdev-0.14.18.dist-info/top_level.txt
iotedgehubdev-0.14.18.dist-info/RECORD
