Metadata-Version: 2.1
Name: iotedgehubdev
Version: 0.14.18
Summary: Azure IoT EdgeHub Dev Tool
Home-page: https://github.com/Azure/iotedgehubdev
Author: iotedgehubdev
Author-email: vsciet@microsoft.com
License: MIT
Platform: any
Classifier: Development Status :: 5 - Production/Stable
Classifier: Environment :: Console
Classifier: Intended Audience :: Developers
Classifier: License :: OSI Approved :: MIT License
Classifier: Operating System :: POSIX
Classifier: Operating System :: MacOS
Classifier: Operating System :: Unix
Classifier: Operating System :: Microsoft :: Windows
Classifier: Programming Language :: Python
Classifier: Programming Language :: Python :: 3
Classifier: Programming Language :: Python :: 3.5
Classifier: Programming Language :: Python :: 3.6
Classifier: Programming Language :: Python :: 3.7
Classifier: Programming Language :: Python :: 3.8
Classifier: Programming Language :: Python :: 3.9
Classifier: Topic :: Software Development :: Libraries :: Python Modules
Requires-Python: >=3.5, <3.10
Requires-Dist: click
Requires-Dist: docker (==5.0.3)
Requires-Dist: pyOpenSSL (==22.0.0)
Requires-Dist: requests (>=2.25.1)
Requires-Dist: applicationinsights (==0.11.9)
Requires-Dist: pyyaml (>=5.4)
Requires-Dist: jsonpath-rw
Requires-Dist: docker-compose (==1.29.1)
Requires-Dist: regex
